comlibpy/__init__.py
comlibpy/func.py
comlibpy/iter.py
comlibpy/math.py
comlibpy/vparam.py
comlibpy/xdict.py
comlibpy/xtree.py
comlibpy-0.1.7.dist-info/LICENSE
comlibpy-0.1.7.dist-info/METADATA
comlibpy-0.1.7.dist-info/WHEEL
comlibpy-0.1.7.dist-info/top_level.txt
comlibpy-0.1.7.dist-info/RECORD
