Metadata-Version: 2.1
Name: comlibpy
Version: 0.1.7
Summary: My short description for my project.
Home-page: https://gitee.com/xwhan/comlib-python
Author: Leo
Author-email: xwhan_@163.com
License: MIT
Platform: UNKNOWN
Classifier: License :: OSI Approved :: MIT License
Classifier: Programming Language :: Python
Classifier: Programming Language :: Python :: 3
Classifier: Programming Language :: Python :: 3.6
Classifier: Programming Language :: Python :: Implementation :: CPython
Classifier: Programming Language :: Python :: Implementation :: PyPy
Requires-Python: >=3.6.0
